{
  "modified": "Fri Oct 15 2021 15:43:53 GMT+0800 (中国标准时间)",
  "width": 120,
  "height": 20,
  "comps": [
    {
      "type": "shape",
      "background": "rgb(255,0,0)",
      "pixelPerfect": true,
      "points": [
        12.13187,
        20,
        0,
        20,
        0,
        14.06594,
        2.00044,
        14.06594,
        1.97538,
        17.75824,
        12.13187,
        17.75824,
        12.13187,
        20
      ],
      "segments": [
        1,
        2,
        2,
        2,
        2,
        2,
        2,
        5
      ]
    },
    {
      "type": "shape",
      "background": "rgb(255,0,0)",
      "pixelPerfect": true,
      "points": [
        107.86813,
        20,
        120,
        20,
        120,
        14.06594,
        117.99956,
        14.06594,
        118.02461,
        17.75824,
        107.86813,
        17.75824,
        107.86813,
        20
      ],
      "segments": [
        1,
        2,
        2,
        2,
        2,
        2,
        2,
        5
      ]
    },
    {
      "type": "shape",
      "background": "rgb(255,0,0)",
      "pixelPerfect": true,
      "points": [
        2.50549,
        1.25055,
        117.49451,
        1.25055,
        117.49451,
        17.25055,
        2.50549,
        17.25055,
        2.50549,
        1.25055
      ],
      "segments": [
        1,
        2,
        2,
        2,
        2,
        5
      ]
    },
    {
      "type": "shape",
      "background": "rgb(242,131,131)",
      "pixelPerfect": true,
      "points": [
        10.93855,
        11.53002,
        10.95364,
        6.12476,
        10.95364,
        6.12476,
        10.95364,
        6.12476,
        109.1937,
        6.3991,
        109.1937,
        6.3991,
        109.1937,
        6.3991,
        109.1786,
        11.80436,
        109.1786,
        11.80436,
        109.1786,
        11.80436,
        10.93855,
        11.53002,
        10.93855,
        11.53002,
        10.93855,
        11.53002
      ],
      "segments": [
        1,
        2,
        3,
        2,
        3,
        2,
        3,
        2,
        3,
        5
      ]
    },
    {
      "type": "shape",
      "background": "rgb(240,29,29)",
      "pixelPerfect": true,
      "points": [
        11.21538,
        6.39561,
        108.92308,
        6.65934,
        108.90989,
        11.53846,
        11.20879,
        11.27473,
        11.22198,
        6.39561,
        10.69451,
        5.86813,
        10.67868,
        11.8022,
        109.44791,
        12.07648,
        109.46374,
        6.14242,
        10.69451,
        5.86681,
        10.69451,
        5.86813
      ],
      "segments": [
        1,
        2,
        2,
        2,
        2,
        1,
        2,
        2,
        2,
        2,
        2,
        5
      ]
    },
    {
      "type": "shape",
      "background": "rgb(245,113,113)",
      "pixelPerfect": true,
      "points": [
        8.02444,
        8.99722,
        10.68098,
        6.34067,
        10.68098,
        6.34067,
        10.68098,
        6.34067,
        13.27133,
        8.93101,
        13.27133,
        8.93101,
        13.27133,
        8.93101,
        10.61478,
        11.58756,
        10.61478,
        11.58756,
        10.61478,
        11.58756,
        8.02444,
        8.99722,
        8.02444,
        8.99722,
        8.02444,
        8.99722
      ],
      "segments": [
        1,
        2,
        3,
        2,
        3,
        2,
        3,
        2,
        3,
        5
      ]
    },
    {
      "type": "shape",
      "background": "rgb(255,0,0)",
      "pixelPerfect": true,
      "points": [
        10.68132,
        6.71473,
        12.89802,
        8.93143,
        10.61538,
        11.21539,
        8.39868,
        8.99736,
        10.68132,
        6.71473,
        10.68132,
        5.96835,
        7.64835,
        9.00132,
        10.61538,
        11.96044,
        13.64835,
        8.92747,
        10.68132,
        5.96835
      ],
      "segments": [
        1,
        2,
        2,
        2,
        2,
        1,
        2,
        2,
        2,
        2,
        5
      ]
    },
    {
      "type": "shape",
      "background": "rgb(245,113,113)",
      "pixelPerfect": true,
      "points": [
        106.79538,
        8.99814,
        109.45193,
        6.3416,
        109.45193,
        6.3416,
        109.45193,
        6.3416,
        112.04227,
        8.93194,
        112.04227,
        8.93194,
        112.04227,
        8.93194,
        109.38572,
        11.58848,
        109.38572,
        11.58848,
        109.38572,
        11.58848,
        106.79538,
        8.99814,
        106.79538,
        8.99814,
        106.79538,
        8.99814
      ],
      "segments": [
        1,
        2,
        3,
        2,
        3,
        2,
        3,
        2,
        3,
        5
      ]
    },
    {
      "type": "shape",
      "background": "rgb(204,96,96)",
      "pixelPerfect": true,
      "points": [
        109.45055,
        6.71473,
        111.66725,
        8.93143,
        109.38461,
        11.21539,
        107.16791,
        8.99736,
        109.45055,
        6.71473,
        109.45055,
        5.96835,
        106.41758,
        9.00132,
        109.38461,
        11.96044,
        112.41758,
        8.92747,
        109.45055,
        5.96835
      ],
      "segments": [
        1,
        2,
        2,
        2,
        2,
        1,
        2,
        2,
        2,
        2,
        5
      ]
    }
  ]
}